README.rst
aggregate_if.py
setup.py
django_aggregate_if.egg-info/PKG-INFO
django_aggregate_if.egg-info/SOURCES.txt
django_aggregate_if.egg-info/dependency_links.txt
django_aggregate_if.egg-info/not-zip-safe
django_aggregate_if.egg-info/requires.txt
django_aggregate_if.egg-info/top_level.txt