Metadata-Version: 1.1
Name: django-aggregate-if
Version: 0.4
Summary: Conditional aggregates for Django, just like the famous SumIf in Excel.
Home-page: http://github.com/henriquebastos/django-aggregate-if/
Author: Henrique Bastos
Author-email: henrique@bastos.net
License: MIT
Platform: any
Classifier: Development Status :: 5 - Production/Stable
Classifier: Framework :: Django
Classifier: Intended Audience :: Developers
Classifier: License :: OSI Approved :: MIT License
Classifier: Natural Language :: English
Classifier: Operating System :: OS Independent
Classifier: Programming Language :: Python
Classifier: Programming Language :: Python :: 2.7
Classifier: Programming Language :: Python :: 3
Classifier: Topic :: Database
Classifier: Topic :: Software Development :: Libraries
